dijkstra/__init__.py
dijkstra/dijkstra.py
dijkstra/node.py
dijkstra_tg-0.1.0.post2.dist-info/LICENSE
dijkstra_tg-0.1.0.post2.dist-info/METADATA
dijkstra_tg-0.1.0.post2.dist-info/WHEEL
dijkstra_tg-0.1.0.post2.dist-info/top_level.txt
dijkstra_tg-0.1.0.post2.dist-info/RECORD
