Metadata-Version: 2.1
Name: dijkstra-tg
Version: 0.1.0.post2
Summary: A simple Dijkstra's Algorithm implementation
Author-email: TOMG-A <im.tomtomon@gmail.com>
Project-URL: Homepage, https://github.com/TOMG-A/DijkstrasAlgorithm
Project-URL: Issues, https://github.com/TOMG-A/DijkstrasAlgorithm/issues
Classifier: Programming Language :: Python :: 3
Classifier: License :: OSI Approved :: MIT License
Classifier: Operating System :: OS Independent
Requires-Python: >=3.8
License-File: LICENSE
